subclassdict/__init__.py
subclassdict/py.typed
subclassdict/subclassdict.py
subclassdict/subclasses.py
subclassdict-0.1.1.dist-info/licenses/LICENSE
subclassdict-0.1.1.dist-info/METADATA
subclassdict-0.1.1.dist-info/WHEEL
subclassdict-0.1.1.dist-info/top_level.txt
subclassdict-0.1.1.dist-info/RECORD
