Metadata-Version: 2.4
Name: subclassdict
Version: 0.1.1
Summary: A TypeDict that allows subclasses of type keys to be used as keys
Author: Odos Matthews
License-Expression: MIT
Project-URL: Homepage, https://github.com/eddiethedean/subclassdict
Project-URL: Repository, https://github.com/eddiethedean/subclassdict
Project-URL: Issues, https://github.com/eddiethedean/subclassdict/issues
Project-URL: Documentation, https://github.com/eddiethedean/subclassdict#readme
Classifier: Development Status :: 4 - Beta
Classifier: Intended Audience :: Developers
Classifier: Programming Language :: Python :: 3
Classifier: Programming Language :: Python :: 3 :: Only
Classifier: Programming Language :: Python :: 3.8
Classifier: Programming Language :: Python :: 3.9
Classifier: Programming Language :: Python :: 3.10
Classifier: Programming Language :: Python :: 3.11
Classifier: Programming Language :: Python :: 3.12
Classifier: Programming Language :: Python :: 3.13
Classifier: Topic :: Software Development :: Libraries :: Python Modules
Classifier: Typing :: Typed
Requires-Python: >=3.8
License-File: LICENSE
Requires-Dist: typedict>=0.0.3
Provides-Extra: dev
Requires-Dist: pytest>=7.0.0; extra == "dev"
Requires-Dist: pytest-cov>=4.0.0; extra == "dev"
Requires-Dist: mypy>=1.0.0; extra == "dev"
Requires-Dist: ruff>=0.1.0; extra == "dev"
Requires-Dist: pre-commit>=3.0.0; extra == "dev"
Requires-Dist: tox>=4.0.0; extra == "dev"
Provides-Extra: test
Requires-Dist: pytest>=7.0.0; extra == "test"
Requires-Dist: pytest-cov>=4.0.0; extra == "test"
Provides-Extra: lint
Requires-Dist: ruff>=0.1.0; extra == "lint"
Requires-Dist: mypy>=1.0.0; extra == "lint"
Dynamic: license-file
